themarcoscorner_sales/settings.py
themarcoscorner_sales-0.0.1.dist-info/METADATA
themarcoscorner_sales-0.0.1.dist-info/WHEEL
themarcoscorner_sales-0.0.1.dist-info/RECORD
